pytket/extensions/aqt/__init__.py
pytket/extensions/aqt/_metadata.py
pytket/extensions/aqt/logger.py
pytket/extensions/aqt/py.typed
pytket/extensions/aqt/backends/__init__.py
pytket/extensions/aqt/backends/aqt.py
pytket/extensions/aqt/backends/aqt_api.py
pytket/extensions/aqt/backends/aqt_job_data.py
pytket/extensions/aqt/backends/aqt_multi_zone.py
pytket/extensions/aqt/backends/config.py
pytket/extensions/aqt/multi_zone_architecture/__init__.py
pytket/extensions/aqt/multi_zone_architecture/compilation_settings.py
pytket/extensions/aqt/multi_zone_architecture/circuit/__init__.py
pytket/extensions/aqt/multi_zone_architecture/circuit/helpers.py
pytket/extensions/aqt/multi_zone_architecture/circuit/multizone_circuit.py
pytket/extensions/aqt/multi_zone_architecture/circuit_routing/__init__.py
pytket/extensions/aqt/multi_zone_architecture/circuit_routing/route_circuit.py
pytket/extensions/aqt/multi_zone_architecture/circuit_routing/routing_config.py
pytket/extensions/aqt/multi_zone_architecture/circuit_routing/routing_ops.py
pytket/extensions/aqt/multi_zone_architecture/circuit_routing/gate_selection/__init__.py
pytket/extensions/aqt/multi_zone_architecture/circuit_routing/gate_selection/gate_selector_protocol.py
pytket/extensions/aqt/multi_zone_architecture/circuit_routing/gate_selection/graph_partition_gate_selection.py
pytket/extensions/aqt/multi_zone_architecture/circuit_routing/gate_selection/greedy_gate_selection.py
pytket/extensions/aqt/multi_zone_architecture/circuit_routing/gate_selection/qubit_tracker.py
pytket/extensions/aqt/multi_zone_architecture/circuit_routing/legacy/__init__.py
pytket/extensions/aqt/multi_zone_architecture/circuit_routing/legacy/greedy_routing.py
pytket/extensions/aqt/multi_zone_architecture/circuit_routing/legacy/route_circuit.py
pytket/extensions/aqt/multi_zone_architecture/circuit_routing/qubit_routing/__init__.py
pytket/extensions/aqt/multi_zone_architecture/circuit_routing/qubit_routing/general_router.py
pytket_aqt-0.40.0.dist-info/licenses/LICENSE
pytket_aqt-0.40.0.dist-info/METADATA
pytket_aqt-0.40.0.dist-info/WHEEL
pytket_aqt-0.40.0.dist-info/top_level.txt
pytket_aqt-0.40.0.dist-info/RECORD
