Metadata-Version: 2.4
Name: pytket-aqt
Version: 0.40.0
Summary: Extension for pytket, TODOPYTKETEXT
Author-email: TKET development team <tket-support@quantinuum.com>
Maintainer-email: TKET development team <tket-support@quantinuum.com>
License:                                  Apache License
Project-URL: documentation, https://tket.quantinuum.com/extensions/pytket-aqt/index.html
Project-URL: source, https://github.com/Quantinuum/pytket-aqt
Project-URL: tracker, https://github.com/Quantinuum/pytket-aqt/issues
Classifier: Environment :: Console
Classifier: Programming Language :: Python :: 3.11
Classifier: Programming Language :: Python :: 3.12
Classifier: Programming Language :: Python :: 3.13
Classifier: Operating System :: MacOS :: MacOS X
Classifier: Operating System :: POSIX :: Linux
Classifier: Operating System :: Microsoft :: Windows
Classifier: Intended Audience :: Developers
Classifier: Intended Audience :: Science/Research
Classifier: Topic :: Scientific/Engineering
Requires-Python: <4.0,>=3.11
License-File: LICENSE
Requires-Dist: pytket>=2.11
Requires-Dist: requests>=2.22
Requires-Dist: types-requests
Requires-Dist: pydantic>=2.0
Requires-Dist: networkx>=3.0
Requires-Dist: sympy>=1.6
Requires-Dist: qiskit-aqt-provider>=1.10.0
Requires-Dist: mtkahypar>=1.5; sys_platform != "win32"
Requires-Dist: numpy<3.0.0,>=2.3.4
Requires-Dist: notebook<8.0.0,>=7.4.7
Requires-Dist: types-networkx>=3.5.0.20251106
Dynamic: license-file
